MANIFEST.in
README.in
README.txt
make_readme.py
make_release.sh
setup.py
TurboFancyFlash.egg-info/PKG-INFO
TurboFancyFlash.egg-info/SOURCES.txt
TurboFancyFlash.egg-info/dependency_links.txt
TurboFancyFlash.egg-info/entry_points.txt
TurboFancyFlash.egg-info/not-zip-safe
TurboFancyFlash.egg-info/requires.txt
TurboFancyFlash.egg-info/top_level.txt
doc/index.html
doc/rest.css
doc/api/api-objects.txt
doc/api/class-tree.html
doc/api/crarr.png
doc/api/epydoc.css
doc/api/epydoc.js
doc/api/fancyflash-module.html
doc/api/fancyflash-pysrc.html
doc/api/fancyflash.release-module.html
doc/api/fancyflash.release-pysrc.html
doc/api/fancyflash.widgets-module.html
doc/api/fancyflash.widgets-pysrc.html
doc/api/fancyflash.widgets.FancyFlashDesc-class.html
doc/api/fancyflash.widgets.FancyFlashDesc.template_c-class.html
doc/api/fancyflash.widgets.FancyFlashWidget-class.html
doc/api/fancyflash.widgets.FancyFlashWidget.template_c-class.html
doc/api/fancyflash.widgets.jslibs-module.html
doc/api/fancyflash.widgets.jslibs-pysrc.html
doc/api/help.html
doc/api/identifier-index.html
doc/api/index.html
doc/api/module-tree.html
doc/api/redirect.html
doc/api/turbogears.widgets.base.MetaDescription-class.html
doc/api/turbogears.widgets.meta.MetaWidget-class.html
fancyflash/__init__.py
fancyflash/release.py
fancyflash/widgets/__init__.py
fancyflash/widgets/jslibs/__init__.py
fancyflash/widgets/jslibs/static/javascript/MochiKit.js
fancyflash/widgets/jslibs/static/javascript/events.js
fancyflash/widgets/static/css/fancyflash.css
fancyflash/widgets/static/css/ie.css
fancyflash/widgets/static/images/access-denied.gif
fancyflash/widgets/static/images/access-denied.png
fancyflash/widgets/static/images/cancel.gif
fancyflash/widgets/static/images/cancel.png
fancyflash/widgets/static/images/error.gif
fancyflash/widgets/static/images/error.png
fancyflash/widgets/static/images/info.gif
fancyflash/widgets/static/images/info.png
fancyflash/widgets/static/images/mail.gif
fancyflash/widgets/static/images/mail.png
fancyflash/widgets/static/images/ok.gif
fancyflash/widgets/static/images/ok.png
fancyflash/widgets/static/images/question.gif
fancyflash/widgets/static/images/question.png
fancyflash/widgets/static/images/refresh.gif
fancyflash/widgets/static/images/refresh.png
