Metadata-Version: 1.0
Name: TurboFancyFlash
Version: 0.1a
Summary: TurboGears extension providing enhanced flash message display functions.
Home-page: http://chrisarndt.de/projects/fancyflash/
Author: Christopher Arndt
Author-email: chris@chrisarndt.de
License: MIT license
Download-URL: http://cheeseshop.python.org/pypi/0.1a
Keywords: turbogears.extension,turbogears.widgets
Platform: UNKNOWN
Classifier: Development Status :: 3 - Alpha
Classifier: Operating System :: OS Independent
Classifier: Programming Language :: Python
Classifier: Topic :: Software Development :: Libraries :: Python Modules
Classifier: Framework :: TurboGears
Classifier: Framework :: TurboGears :: Widgets
